[
  {
    "id": "monumento-heroes",
    "nombre": "Monumento a los Héroes de la Restauración",
    "nombre_en": "Monument to the Heroes of the Restoration",
    "categoria": "turismo",
    "subcategoria": "monumentos",
    "descripcion": "Ícono de Santiago con vistas panorámicas de la ciudad.",
    "descripcion_en": "Santiago's iconic monument with panoramic city views.",
    "lat": 19.4517,
    "lng": -70.697,
    "foto": "/images/lugares/monumento-heroes.jpg",
    "google_maps_url": "https://maps.google.com/?q=Monumento+Santiago+Republica+Dominicana"
  },
  {
    "id": "parque-duarte",
    "nombre": "Parque Duarte",
    "nombre_en": "Duarte Park",
    "categoria": "turismo",
    "subcategoria": "parques",
    "descripcion": "Plaza histórica en el corazón del centro, rodeada de arquitectura colonial.",
    "descripcion_en": "Historic square at the city center, surrounded by colonial architecture.",
    "lat": 19.4498,
    "lng": -70.6923,
    "foto": "/images/lugares/parque-duarte.jpg",
    "google_maps_url": "https://maps.google.com/?q=Parque+Duarte+Santiago"
  },
  {
    "id": "museo-tabaco",
    "nombre": "Museo del Tabaco",
    "nombre_en": "Tobacco Museum",
    "categoria": "turismo",
    "subcategoria": "museos",
    "descripcion": "Descubre la historia del tabaco dominicano, patrimonio de Santiago.",
    "descripcion_en": "Discover the history of Dominican tobacco, Santiago's heritage.",
    "lat": 19.4505,
    "lng": -70.6918,
    "foto": "/images/lugares/museo-tabaco.jpg",
    "google_maps_url": "https://maps.google.com/?q=Museo+del+Tabaco+Santiago"
  },
  {
    "id": "centro-leon",
    "nombre": "Centro León",
    "nombre_en": "Centro León",
    "categoria": "turismo",
    "subcategoria": "museos",
    "descripcion": "Centro cultural con arte dominicano contemporáneo y exposiciones temporales.",
    "descripcion_en": "Cultural center featuring contemporary Dominican art and rotating exhibits.",
    "lat": 19.4675,
    "lng": -70.7074,
    "foto": "/images/lugares/centro-leon.jpg",
    "google_maps_url": "https://maps.google.com/?q=Centro+Leon+Santiago"
  },
  {
    "id": "catedral-santiago",
    "nombre": "Catedral de Santiago Apóstol",
    "nombre_en": "Santiago Apostle Cathedral",
    "categoria": "turismo",
    "subcategoria": "monumentos",
    "descripcion": "Catedral neoclásica del siglo XIX frente al Parque Duarte.",
    "descripcion_en": "Nineteenth-century neoclassical cathedral facing Duarte Park.",
    "lat": 19.4492,
    "lng": -70.6924,
    "foto": "/images/lugares/catedral.jpg",
    "google_maps_url": "https://maps.google.com/?q=Catedral+Santiago+Apostol"
  },
  {
    "id": "rancho-camaronero",
    "nombre": "El Rancho Camaronero",
    "nombre_en": "El Rancho Camaronero",
    "categoria": "gastronomia",
    "subcategoria": "restaurante-lujo",
    "descripcion": "Alta cocina dominicana con énfasis en mariscos y ambiente elegante.",
    "descripcion_en": "Upscale Dominican cuisine focused on seafood in an elegant setting.",
    "lat": 19.4588,
    "lng": -70.6962,
    "foto": "/images/lugares/camaronero.jpg",
    "google_maps_url": "https://maps.google.com/?q=El+Rancho+Camaronero+Santiago"
  },
  {
    "id": "sakura-sushi",
    "nombre": "Sakura Sushi Bar",
    "nombre_en": "Sakura Sushi Bar",
    "categoria": "gastronomia",
    "subcategoria": "japones",
    "descripcion": "Sushi y cocina japonesa contemporánea en ambiente íntimo.",
    "descripcion_en": "Sushi and contemporary Japanese cuisine in an intimate setting.",
    "lat": 19.4601,
    "lng": -70.7003,
    "foto": "/images/lugares/sakura.jpg",
    "google_maps_url": "https://maps.google.com/?q=Sakura+Sushi+Santiago"
  },
  {
    "id": "hacienda-mexicana",
    "nombre": "Hacienda Mexicana",
    "nombre_en": "Hacienda Mexicana",
    "categoria": "gastronomia",
    "subcategoria": "mexicano",
    "descripcion": "Auténticos tacos, mezcales y platos tradicionales de México.",
    "descripcion_en": "Authentic tacos, mezcal and traditional Mexican dishes.",
    "lat": 19.4562,
    "lng": -70.6988,
    "foto": "/images/lugares/hacienda.jpg",
    "google_maps_url": "https://maps.google.com/?q=Hacienda+Mexicana+Santiago"
  },
  {
    "id": "arepas-bogota",
    "nombre": "Arepas de Bogotá",
    "nombre_en": "Arepas de Bogotá",
    "categoria": "gastronomia",
    "subcategoria": "colombiano",
    "descripcion": "Cocina colombiana casera: arepas, bandeja paisa y más.",
    "descripcion_en": "Home-style Colombian food: arepas, bandeja paisa and more.",
    "lat": 19.4544,
    "lng": -70.695,
    "foto": "/images/lugares/arepas.jpg",
    "google_maps_url": "https://maps.google.com/?q=Arepas+Bogota+Santiago"
  },
  {
    "id": "cafe-monte",
    "nombre": "Café del Monte",
    "nombre_en": "Café del Monte",
    "categoria": "gastronomia",
    "subcategoria": "accesible",
    "descripcion": "Café de especialidad, desayunos y almuerzos a buen precio.",
    "descripcion_en": "Specialty coffee, breakfast and lunch at fair prices.",
    "lat": 19.4521,
    "lng": -70.6935,
    "foto": "/images/lugares/cafe-monte.jpg",
    "google_maps_url": "https://maps.google.com/?q=Cafe+del+Monte+Santiago"
  },
  {
    "id": "kah-kow",
    "nombre": "Kah Kow Experience",
    "nombre_en": "Kah Kow Experience",
    "categoria": "entretenimiento",
    "subcategoria": "actividades",
    "descripcion": "Tour interactivo del cacao dominicano con cata de chocolates.",
    "descripcion_en": "Interactive Dominican cacao tour with chocolate tasting.",
    "lat": 19.4683,
    "lng": -70.708,
    "foto": "/images/lugares/kahkow.jpg",
    "google_maps_url": "https://maps.google.com/?q=Kah+Kow+Experience+Santiago"
  },
  {
    "id": "alcazar-lounge",
    "nombre": "Alcázar Rooftop Lounge",
    "nombre_en": "Alcázar Rooftop Lounge",
    "categoria": "entretenimiento",
    "subcategoria": "vida-nocturna",
    "descripcion": "Rooftop con cocteles de autor y vistas al Monumento.",
    "descripcion_en": "Rooftop with signature cocktails and Monument views.",
    "lat": 19.4525,
    "lng": -70.6977,
    "foto": "/images/lugares/alcazar.jpg",
    "google_maps_url": "https://maps.google.com/?q=Alcazar+Rooftop+Santiago"
  },
  {
    "id": "teatro-cibao",
    "nombre": "Gran Teatro del Cibao",
    "nombre_en": "Gran Teatro del Cibao",
    "categoria": "entretenimiento",
    "subcategoria": "eventos",
    "descripcion": "Principal sala de conciertos, ópera y teatro de la región.",
    "descripcion_en": "The region's main venue for concerts, opera and theater.",
    "lat": 19.4672,
    "lng": -70.6886,
    "foto": "/images/lugares/teatro.jpg",
    "google_maps_url": "https://maps.google.com/?q=Gran+Teatro+del+Cibao"
  },
  {
    "id": "bolera-metro",
    "nombre": "Metro Bowling",
    "nombre_en": "Metro Bowling",
    "categoria": "entretenimiento",
    "subcategoria": "centros-diversion",
    "descripcion": "Centro de entretenimiento familiar con boliche, arcade y billar.",
    "descripcion_en": "Family entertainment center with bowling, arcade and billiards.",
    "lat": 19.4456,
    "lng": -70.705,
    "foto": "/images/lugares/bolera.jpg",
    "google_maps_url": "https://maps.google.com/?q=Metro+Bowling+Santiago"
  },
  {
    "id": "ahi-bar",
    "nombre": "Ahí Bar",
    "nombre_en": "Ahí Bar",
    "categoria": "entretenimiento",
    "subcategoria": "vida-nocturna",
    "descripcion": "Bar de coctelería clásica con música en vivo los fines de semana.",
    "descripcion_en": "Classic cocktail bar with live music on weekends.",
    "lat": 19.4549,
    "lng": -70.6992,
    "foto": "/images/lugares/ahi.jpg",
    "google_maps_url": "https://maps.google.com/?q=Ahi+Bar+Santiago"
  }
]
